LICENSE
README.rst
setup.py
getchinamap/__init__.py
getchinamap/getchinamap.py
getchinamap.egg-info/PKG-INFO
getchinamap.egg-info/SOURCES.txt
getchinamap.egg-info/dependency_links.txt
getchinamap.egg-info/requires.txt
getchinamap.egg-info/top_level.txt
getchinamap/datasets/AMap_adcode_citycode_20210406.csv
getchinamap/datasets/world_for_china