Metadata-Version: 2.1
Name: getchinamap
Version: 1.0.7
Summary: get china map data from Amap
Home-page: https://github.com/yuanzhoulvpi2017/chinamap
Author: yuanzhoulvpi2017
Author-email: 1582034172@qq.com
License: BSD License
Platform: all
Classifier: Intended Audience :: Developers
Classifier: Operating System :: OS Independent
Classifier: Natural Language :: Chinese (Simplified)
Classifier: Programming Language :: Python
Classifier: Programming Language :: Python :: 3.7
Classifier: Programming Language :: Python :: 3.8
Classifier: Programming Language :: Python :: 3.9
Classifier: Programming Language :: Python :: 3.10
Classifier: Topic :: Software Development :: Libraries
License-File: LICENSE
